borsait/__init__.py
borsait/main.py
borsait-0.5.0.dist-info/METADATA
borsait-0.5.0.dist-info/WHEEL
borsait-0.5.0.dist-info/entry_points.txt
borsait-0.5.0.dist-info/RECORD
